RAGnificent/RAGnificent.py
RAGnificent/__init__.py
base_model/__init__.py
base_model/base_rag_model.py
graph/__init__.py
graph/graph.py
llm/__init__.py
llm/baseLLM.py
nodes/__init__.py
nodes/nodes.py
params/__init__.py
params/agent_params.py
ragnificent-1.0.dist-info/licenses/LICENSE
state/__init__.py
state/state.py
ragnificent-1.0.dist-info/METADATA
ragnificent-1.0.dist-info/WHEEL
ragnificent-1.0.dist-info/top_level.txt
ragnificent-1.0.dist-info/RECORD
