Metadata-Version: 2.4
Name: RAGnificent
Version: 1.0
Summary: A simple RAG chatbot supporting multiple LLM providers
Home-page: https://github.com/Abul-Farhad/simple-rag
Author: K. M. Abul Farhad-Ibn-Alam
Author-email: abulfarhad.ibnalam@gmail.com
License: Custom
Project-URL: Source, https://github.com/Abul-Farhad/simple-rag
Keywords: llm chatbot rag openai groq gemini
Classifier: Programming Language :: Python :: 3
Classifier: License :: Other/Proprietary License
Classifier: Intended Audience :: Developers
Classifier: Topic :: Software Development :: Libraries :: Python Modules
Classifier: Topic :: Scientific/Engineering :: Artificial Intelligence
Requires-Python: >=3.9
License-File: LICENSE
Requires-Dist: pydantic
Requires-Dist: langchain
Requires-Dist: langchain-core
Requires-Dist: langchain-community
Requires-Dist: langchain-groq
Requires-Dist: langchain-openai
Requires-Dist: langgraph
Requires-Dist: python-dotenv
Dynamic: author
Dynamic: author-email
Dynamic: classifier
Dynamic: description
Dynamic: description-content-type
Dynamic: home-page
Dynamic: keywords
Dynamic: license
Dynamic: license-file
Dynamic: project-url
Dynamic: requires-dist
Dynamic: requires-python
Dynamic: summary
